{
  "variants": {
    "facing=north,activated=true": { "model": "mbackrooms:block/cardboard_box_opened" },
    "facing=north,activated=false": { "model": "mbackrooms:block/cardboard_box" },

    "facing=south,activated=true": { "model": "mbackrooms:block/cardboard_box_opened", "y": 180 },
    "facing=south,activated=false": { "model": "mbackrooms:block/cardboard_box", "y": 180 },

    "facing=west,activated=true": { "model": "mbackrooms:block/cardboard_box_opened", "y": 270 },
    "facing=west,activated=false": { "model": "mbackrooms:block/cardboard_box", "y": 270 },

    "facing=east,activated=true": { "model": "mbackrooms:block/cardboard_box_opened", "y": 90 },
    "facing=east,activated=false": { "model": "mbackrooms:block/cardboard_box", "y": 90 }
  }
}
